{
    "$id": "newCustomer",
    "type": "object",
    "properties": {
        "email": {
            "type": "string",
            "format": "emailAddress"
        },
        "firstName": {
            "type": "string"
        },
        "lastName": {
            "type": "string"
        },
        "address1": {
            "type": "string"
        },
        "address2": {
            "type": "string"
        },
        "country": {
            "type": "string"
        },
        "state": {
            "type": "string"
        },
        "postcode": {
            "type": "string"
        },
        "phone": {
            "type": "string"
        },
        "password": {
            "type": "string",
            "isNotEmpty": true
        },
        "peerplaysAccountId": {
            "type": "string"
        },
        "peerplaysAccountName": {
            "type": "string"
        },
        "peerIDAccessToken": {
            "type": "string"
        },
        "peerIDRefreshToken": {
            "type": "string"
        },
        "peerIDTokenExpires": {
            "type": "string"
        }
    },
    "required": [
        "email",
        "password"
    ]
}